{
  "type": "FeatureCollection",
  "features": [
    {
      "type": "Feature",
      "properties": {
        "id": "4305108",
        "name": "Caxias do Sul"},
      "geometry": {
        "type": "Polygon",
        "coordinates": [
          [
            [
              -51.28314971923828,
              -29.246865023171303
            ],
            [
              -51.08745574951171,
              -29.246865023171303
            ],
            [
              -51.08745574951171,
              -29.0885768689394
            ],
            [
              -51.28314971923828,
              -29.0885768689394
            ],
            [
              -51.28314971923828,
              -29.246865023171303
            ]
          ]
        ]
      }
    }
  ]
}
